qresp_config/__init__.py
qresp_config/__main__.py
qresp_config/qresp_config.py
qresp_config/scripts/__init__.py
qresp_config/scripts/docopt.py
qresp_config-1.0.0.dist-info/METADATA
qresp_config-1.0.0.dist-info/RECORD
qresp_config-1.0.0.dist-info/WHEEL
qresp_config-1.0.0.dist-info/entry_points.txt
qresp_config-1.0.0.dist-info/top_level.txt
