Metadata-Version: 2.1
Name: qresp-config
Version: 1.0.0
Summary: Python command line application to configure qresp.
Home-page: UNKNOWN
Author: Aditya Tanikanti, Marco Govoni
Author-email: datadev@lists.uchicago.edu
License: MIT
Platform: UNKNOWN
Requires-Python: >=3.0
Requires-Dist: configparser
